at_common_functions/__init__.py
at_common_functions/example/__init__.py
at_common_functions/llm/__init__.py
at_common_functions/llm/impls/inference.py
at_common_functions/news/__init__.py
at_common_functions/news/impls/general.py
at_common_functions/news/impls/stock.py
at_common_functions/stock/__init__.py
at_common_functions/stock/impls/candlestick.py
at_common_functions/stock/impls/indicator.py
at_common_functions/stock/impls/overview.py
at_common_functions/stock/impls/quotation.py
at_common_functions/stock/impls/financial/__init__.py
at_common_functions/stock/impls/financial/analysis.py
at_common_functions/utils/openai.py
at_common_functions/utils/storage.py
at_common_functions-1.0.26.dist-info/METADATA
at_common_functions-1.0.26.dist-info/WHEEL
at_common_functions-1.0.26.dist-info/top_level.txt
at_common_functions-1.0.26.dist-info/RECORD
