Metadata-Version: 2.2
Name: at_common_functions
Version: 1.0.26
Summary: A Python package providing common functions for workflow operations.
Author-email: Rui Chen <apextrader.ai@gmail.com>
Project-URL: Homepage, https://github.com/apex-trader/at-common-functions
Project-URL: Bug Tracker, https://github.com/apex-trader/at-common-functions/issues
Classifier: Programming Language :: Python :: 3
Classifier: License :: OSI Approved :: MIT License
Classifier: Operating System :: OS Independent
Requires-Python: >=3.11
Requires-Dist: at_common_workflow>=1.2.9
Requires-Dist: SQLAlchemy>=2.0.36
Requires-Dist: at-common-models>=0.1.13
Requires-Dist: aiomysql>=0.2.0
Requires-Dist: greenlet>=3.1.1
Requires-Dist: openai>=1.58.1
Requires-Dist: python-dotenv>=1.0.1
Requires-Dist: httpx>=0.28.1
Requires-Dist: tenacity>=9.0.0
Requires-Dist: jinja2>=3.1.5
Requires-Dist: jiter>=0.8.2
Requires-Dist: pandas>=2.2.3
Requires-Dist: numpy>=2.2.1
Requires-Dist: babel>=2.16.0
Provides-Extra: dev
Requires-Dist: pytest>=8.3.4; extra == "dev"
Requires-Dist: pytest-asyncio>=0.25.0; extra == "dev"
Requires-Dist: build>=1.0.0; extra == "dev"
Requires-Dist: twine>=4.0.0; extra == "dev"
